AUTHORS.md
LICENSE
MANIFEST.in
README.rst
setup.cfg
setup.py
django_menu_generator.egg-info/PKG-INFO
django_menu_generator.egg-info/SOURCES.txt
django_menu_generator.egg-info/dependency_links.txt
django_menu_generator.egg-info/top_level.txt
docs/Makefile
docs/authors.rst
docs/changelog.rst
docs/conf.py
docs/contribute.rst
docs/credits.rst
docs/index.rst
docs/install.rst
docs/license.rst
docs/make.bat
docs/menugeneration.rst
docs/support.rst
docs/tests.rst
docs/urls.rst
docs/usage.rst
docs/validators.rst
menu_generator/__init__.py
menu_generator/apps.py
menu_generator/defaults.py
menu_generator/menu.py
menu_generator/utils.py
menu_generator/validators.py
menu_generator/__pycache__/__init__.cpython-35.pyc
menu_generator/__pycache__/__init__.cpython-36.pyc
menu_generator/__pycache__/__init__.cpython-37.pyc
menu_generator/__pycache__/apps.cpython-35.pyc
menu_generator/__pycache__/apps.cpython-36.pyc
menu_generator/__pycache__/apps.cpython-37.pyc
menu_generator/__pycache__/defaults.cpython-35.pyc
menu_generator/__pycache__/defaults.cpython-36.pyc
menu_generator/__pycache__/defaults.cpython-37.pyc
menu_generator/__pycache__/menu.cpython-35.pyc
menu_generator/__pycache__/menu.cpython-36.pyc
menu_generator/__pycache__/menu.cpython-37.pyc
menu_generator/__pycache__/utils.cpython-35.pyc
menu_generator/__pycache__/utils.cpython-36.pyc
menu_generator/__pycache__/utils.cpython-37.pyc
menu_generator/__pycache__/validators.cpython-35.pyc
menu_generator/__pycache__/validators.cpython-36.pyc
menu_generator/__pycache__/validators.cpython-37.pyc
menu_generator/templatetags/__init__.py
menu_generator/templatetags/menu_generator.py
menu_generator/templatetags/utils.py
menu_generator/templatetags/__pycache__/__init__.cpython-35.pyc
menu_generator/templatetags/__pycache__/__init__.cpython-36.pyc
menu_generator/templatetags/__pycache__/__init__.cpython-37.pyc
menu_generator/templatetags/__pycache__/menu_generator.cpython-35.pyc
menu_generator/templatetags/__pycache__/menu_generator.cpython-36.pyc
menu_generator/templatetags/__pycache__/menu_generator.cpython-37.pyc
menu_generator/templatetags/__pycache__/utils.cpython-35.pyc
